README.rst
setup.py
stormbot_music/__init__.py
stormbot_music.egg-info/PKG-INFO
stormbot_music.egg-info/SOURCES.txt
stormbot_music.egg-info/dependency_links.txt
stormbot_music.egg-info/entry_points.txt
stormbot_music.egg-info/requires.txt
stormbot_music.egg-info/top_level.txt