Metadata-Version: 1.1
Name: stormbot-music
Version: 2.0b1
Summary: music plugin for stormbot
Home-page: https://github.com/manoir/stormbot-music
Author: Paul Fariello
Author-email: paul@fariello.eu
License: UNKNOWN
Platform: UNKNOWN
Classifier: Environment :: Console
Classifier: Operating System :: POSIX
Classifier: Topic :: Communications :: Chat
Classifier: Programming Language :: Python
